{
  "document_id": "104",
  "chunk_type": "semantic",
  "language": "en",
  "num_chunks": 5,
  "chunks": [
    {
      "hash": "1beb47fd8ad641ed",
      "content": "The success of its football team made Notre Dame a household name. The success of Note Dame reflected rising status of Irish Americans and Catholics in the 1920s. Catholics rallied up around the team and listen to the games on the radio, especially when it knocked off the schools that symbolized the Protestant establishment in America — Harvard, Yale, Princeton, and Army.",
      "start_idx": 0,
      "end_idx": 319,
      "sequence_num": 0,
      "metadata": {
        "topic": "Notre Dame's football success and its cultural significance",
        "keywords": [
          "Notre Dame",
          "football",
          "Irish Americans",
          "Catholics",
          "1920s"
        ]
      },
      "chunk_type": "semantic"
    },
    {
      "hash": "f8991b67c93c6102",
      "content": "Yet this role as high-profile flagship institution of Catholicism made it an easy target of anti-Catholicism. The most remarkable episode of violence was the clash between Notre Dame students and the Ku Klux Klan in 1924. Nativism and anti-Catholicism, especially when directed towards immigrants, were cornerstones of the KKK's rhetoric, and Notre Dame was seen as a symbol of the threat posed by the Catholic Church.",
      "start_idx": 320,
      "end_idx": 487,
      "sequence_num": 1,
      "metadata": {
        "topic": "Anti-Catholicism and the KKK's opposition to Notre Dame",
        "keywords": [
          "anti-Catholicism",
          "KKK",
          "violence",
          "1924",
          "Nativism"
        ]
      },
      "chunk_type": "semantic"
    },
    {
      "hash": "c9289b801c7d3871",
      "content": "The Klan decided to have a week-long Klavern in South Bend. Clashes with the student body started on March 17, when students, aware of the anti-Catholic animosity, blocked the Klansmen from descending from their trains in the South Bend station and ripped the KKK clothes and regalia.",
      "start_idx": 488,
      "end_idx": 586,
      "sequence_num": 2,
      "metadata": {
        "topic": "Clashes between Notre Dame students and the KKK",
        "keywords": [
          "Klavern",
          "South Bend",
          "students",
          "clashes",
          "anti-Catholic"
        ]
      },
      "chunk_type": "semantic"
    },
    {
      "hash": "da8fd2cfb1308e78",
      "content": "On May 19 thousands of students massed downtown protesting the Klavern, and only the arrival of college president Fr. Matthew Walsh prevented any further clashes. The next day, football coach Knute Rockne spoke at a campus rally and implored the students to obey the college president and refrain from further violence.",
      "start_idx": 587,
      "end_idx": 688,
      "sequence_num": 3,
      "metadata": {
        "topic": "Student protests and leadership response",
        "keywords": [
          "protests",
          "Fr. Matthew Walsh",
          "Knute Rockne",
          "violence",
          "campus rally"
        ]
      },
      "chunk_type": "semantic"
    },
    {
      "hash": "1a030a8599e744da",
      "content": "A few days later the Klavern broke up, but the hostility shown by the students was an omen and a contribution to the downfall of the KKK in Indiana.",
      "start_idx": 689,
      "end_idx": 754,
      "sequence_num": 4,
      "metadata": {
        "topic": "Impact of student actions on the KKK's decline",
        "keywords": [
          "Klavern",
          "downfall",
          "KKK",
          "Indiana",
          "student actions"
        ]
      },
      "chunk_type": "semantic"
    }
  ],
  "created_at": "2025-08-10T10:36:32.084235",
  "embedding_model": "text-embedding-3-large",
  "additional_metadata": {
    "run_id": "exp_20250810_081040",
    "language": "en",
    "query_id": null,
    "model": "text-embedding-3-large"
  }
}