{
  "document_id": "17",
  "chunk_type": "semantic",
  "language": "en",
  "num_chunks": 3,
  "chunks": [
    {
      "hash": "437fc9a47e4a4b07",
      "content": "The College of Engineering was established in 1920, however, early courses in civil and mechanical engineering were a part of the College of Science since the 1870s.",
      "start_idx": 0,
      "end_idx": 139,
      "sequence_num": 0,
      "metadata": {
        "topic": "History of the College of Engineering",
        "keywords": [
          "College of Engineering",
          "history",
          "civil engineering",
          "mechanical engineering"
        ]
      },
      "chunk_type": "semantic"
    },
    {
      "hash": "0a5eb40adb6d270a",
      "content": "Today the college, housed in the Fitzpatrick, Cushing, and Stinson-Remick Halls of Engineering, includes five departments of study – aerospace and mechanical engineering, chemical and biomolecular engineering, civil engineering and geological sciences, computer science and engineering, and electrical engineering – with eight B.S. degrees offered.",
      "start_idx": 140,
      "end_idx": 366,
      "sequence_num": 1,
      "metadata": {
        "topic": "Current Structure and Departments",
        "keywords": [
          "departments",
          "B.S. degrees",
          "engineering halls"
        ]
      },
      "chunk_type": "semantic"
    },
    {
      "hash": "af05a251d2d205be",
      "content": "Additionally, the college offers five-year dual degree programs with the Colleges of Arts and Letters and of Business awarding additional B.A. and Master of Business Administration (MBA) degrees, respectively.",
      "start_idx": 367,
      "end_idx": 487,
      "sequence_num": 2,
      "metadata": {
        "topic": "Dual Degree Programs",
        "keywords": [
          "dual degree",
          "Colleges of Arts and Letters",
          "MBA"
        ]
      },
      "chunk_type": "semantic"
    }
  ],
  "created_at": "2025-08-10T09:37:20.922952",
  "embedding_model": "text-embedding-3-large",
  "additional_metadata": {
    "run_id": "exp_20250810_081040",
    "language": "en",
    "query_id": null,
    "model": "text-embedding-3-large"
  }
}