{
  "document_id": "313",
  "chunk_type": "semantic",
  "language": "en",
  "num_chunks": 3,
  "chunks": [
    {
      "hash": "2b3b391ee0ca2dcd",
      "content": "Beyoncé Giselle Knowles was born in Houston, Texas, to Celestine Ann \"Tina\" Knowles (née Beyincé), a hairdresser and salon owner, and Mathew Knowles, a Xerox sales manager. Beyoncé's name is a tribute to her mother's maiden name.",
      "start_idx": 0,
      "end_idx": 218,
      "sequence_num": 0,
      "metadata": {
        "topic": "Beyoncé's early life and family background",
        "keywords": [
          "Beyoncé",
          "birth",
          "family"
        ]
      },
      "chunk_type": "semantic"
    },
    {
      "hash": "d7673e014c0e29c4",
      "content": "Beyoncé's younger sister Solange is also a singer and a former member of Destiny's Child. Mathew is African-American, while Tina is of Louisiana Creole descent (with African, Native American, French, Cajun, and distant Irish and Spanish ancestry).",
      "start_idx": 219,
      "end_idx": 366,
      "sequence_num": 1,
      "metadata": {
        "topic": "Family and heritage",
        "keywords": [
          "Solange",
          "Destiny's Child",
          "heritage"
        ]
      },
      "chunk_type": "semantic"
    },
    {
      "hash": "fe5d1cef3e1989fe",
      "content": "Through her mother, Beyoncé is a descendant of Acadian leader Joseph Broussard. She was raised in a Methodist household.",
      "start_idx": 367,
      "end_idx": 436,
      "sequence_num": 2,
      "metadata": {
        "topic": "Ancestry and upbringing",
        "keywords": [
          "ancestry",
          "Joseph Broussard",
          "Methodist"
        ]
      },
      "chunk_type": "semantic"
    }
  ],
  "created_at": "2025-08-10T10:21:34.101107",
  "embedding_model": "text-embedding-3-large",
  "additional_metadata": {
    "run_id": "exp_20250810_081040",
    "language": "en",
    "query_id": null,
    "model": "text-embedding-3-large"
  }
}