{
  "document_id": "171",
  "chunk_type": "recursive",
  "language": "en",
  "num_chunks": 2,
  "chunks": [
    {
      "hash": "d11a4d0f2a75facb",
      "content": "The School of Architecture was established in 1899, although degrees in architecture were first awarded by the university in 1898. Today the school, housed in Bond Hall, offers a five-year undergraduate program leading to the Bachelor of Architecture degree. All undergraduate students study the third year of the program in Rome. The university is globally recognized for its Notre Dame School of Architecture, a faculty that teaches (pre-modernist) traditional and classical architecture and urban planning (e.",
      "start_idx": 0,
      "end_idx": 512,
      "sequence_num": 0,
      "metadata": {
        "chunk_overlap": 50
      },
      "chunk_type": "recursive"
    },
    {
      "hash": "26e167b11619634d",
      "content": " and classical architecture and urban planning (e.g. following the principles of New Urbanism and New Classical Architecture). It also awards the renowned annual Driehaus Architecture Prize.",
      "start_idx": 462,
      "end_idx": 652,
      "sequence_num": 1,
      "metadata": {
        "chunk_overlap": 50
      },
      "chunk_type": "recursive"
    }
  ],
  "created_at": "2025-08-10T12:57:04.576716",
  "embedding_model": "text-embedding-3-large",
  "additional_metadata": {
    "run_id": "exp_20250810_081040",
    "language": "en",
    "query_id": null,
    "model": "text-embedding-3-large"
  }
}