{
  "document_id": "132",
  "chunk_type": "query_aware",
  "language": "en",
  "num_chunks": 1,
  "chunks": [
    {
      "hash": "a86a63dc45fb4db0",
      "content": "He increased the faculty by more than 500 professors;",
      "start_idx": 134,
      "end_idx": 174,
      "sequence_num": 0,
      "metadata": {
        "relevance_score": 1.0,
        "relevance_reason": "This directly answers the question about the increase in the number of professors under Malloy.",
        "answer_contribution": "Provides the specific amount of increase in faculty.",
        "keywords": [
          "increased",
          "faculty",
          "professors"
        ],
        "query_analysis": {
          "question_type": "information",
          "key_entities": [
            "professors",
            "Notre Dame",
            "Malloy"
          ],
          "keywords": [
            "amount",
            "increased"
          ],
          "required_info": [
            "amount of professors",
            "increase under Malloy"
          ],
          "complexity": "simple"
        },
        "coverage": "100%"
      },
      "chunk_type": "query_aware"
    }
  ],
  "created_at": "2025-08-10T12:00:44.909958",
  "embedding_model": "text-embedding-3-large",
  "additional_metadata": {
    "run_id": "exp_20250810_081040",
    "language": "en",
    "query_id": "132",
    "model": "text-embedding-3-large"
  }
}