{
  "document_id": "4",
  "chunk_type": "query_aware",
  "language": "en",
  "num_chunks": 1,
  "chunks": [
    {
      "hash": "4b12e5af17d526d6",
      "content": "Atop the Main Building's gold dome is a golden statue of the Virgin Mary.",
      "start_idx": 0,
      "end_idx": 73,
      "sequence_num": 0,
      "metadata": {
        "relevance_score": 1.0,
        "relevance_reason": "This sentence directly answers the question about what is on top of the Main Building.",
        "answer_contribution": "Identifies the golden statue of the Virgin Mary as the object sitting atop the Main Building.",
        "keywords": [
          "Main Building",
          "gold dome",
          "golden statue",
          "Virgin Mary"
        ],
        "query_analysis": {
          "question_type": "information",
          "key_entities": [
            "Main Building",
            "Notre Dame"
          ],
          "keywords": [
            "sits on top",
            "Main Building",
            "Notre Dame"
          ],
          "required_info": [
            "what is on top of the Main Building"
          ],
          "complexity": "simple"
        },
        "coverage": "100%"
      },
      "chunk_type": "query_aware"
    }
  ],
  "created_at": "2025-08-10T11:39:54.709381",
  "embedding_model": "text-embedding-3-large",
  "additional_metadata": {
    "run_id": "exp_20250810_081040",
    "language": "en",
    "query_id": "4",
    "model": "text-embedding-3-large"
  }
}